Workbook

Sheet Exec Summary
A1: AegisIQ — Executive Summary
A2: AWM Monitoring & Testing Program | Synthetic data, demonstration purposes
A4: CONTROLS IN SCOPE | C4: RATED RED (latest) | E4: RATED AMBER (latest) | G4: RATED GREEN (latest)
A5: =COUNTA('Control Scorecard'!A5:A17) -> 13 | C5: =COUNTIF('Control Scorecard'!H5:H17,"Red") -> 4 | E5: =COUNTIF('Control Scorecard'!H5:H17,"Amber") -> 2 | G5: =COUNTIF('Control Scorecard'!H5:H17,"Green") -> 7
A9: HIGH/CRITICAL RESIDUAL RISK | C9: OPEN REMEDIATION ACTIONS | E9: OVERDUE VS. SLA | G9: AVG PASS RATE (latest)
A10: =COUNTIF('Control Scorecard'!J5:J17,"High")+COUNTIF('Control Scorecard'!J5:J17,"Critical") -> 2 | C10: =COUNTA(Data_RemediationActions!A2:A383) -> 382 | E10: =COUNTIF(Data_RemediationActions!J2:J383,"Overdue") -> 201 | G10: =AVERAGE('Control Scorecard'!F5:F17) -> 0.90325385
A15: Data Quality Log — Ingestion & Cleaning Layer
A16: table | B16: issue | C16: affected_rows | D16: action_taken
A17: trades | B17: Duplicate rows on key 'trade_id' | C17: 43 | D17: Removed, kept first occurrence
A18: trades | B18: Timestamp format drift in 'execution_timestamp' ('/' vs '-') | C18: 1194 | D18: Normalized to ISO 'YYYY-MM-DD HH:MM:SS' format
A19: trades | B19: Missing required field 'quantity' | C19: 140 | D19: Flagged as Data-Quality Exception (not testable, not silently dropped)
A20: trades | B20: Missing required field 'execution_price' | C20: 142 | D20: Flagged as Data-Quality Exception (not testable, not silently dropped)
A21: trades | B21: Negative quantity | C21: 29 | D21: Flagged as Data-Quality Exception
A22: trades | B22: Zero/negative execution price | C22: 14 | D22: Flagged as Data-Quality Exception
A23: fee_calculations | B23: Missing required field 'billed_fee' | C23: 29 | D23: Flagged as Data-Quality Exception (not testable, not silently dropped)

Sheet Control Scorecard
A1: AegisIQ — Control Scorecard
A2: Latest tested period per control, pulled live from Data_ControlResults / Data_RiskScores
A4: Control ID | B4: Control Name | C4: Process | D4: Latest Period | E4: Population | F4: Pass Rate | G4: KRI Threshold | H4: RAG Status | I4: Control Effectiveness | J4: Residual Risk | K4: Open Exceptions
A5: TC-01 | B5: =IFERROR(INDEX(Data_RiskScores!$B$2:$B$14,MATCH($A5,Data_RiskScores!$A$2:$A$14,0)),"") -> Allocation Timeliness | C5: =IFERROR(INDEX(Data_RiskScores!$C$2:$C$14,MATCH($A5,Data_RiskScores!$A$2:$A$14,0)),"") -> Trade Allocation & Execution | D5: =IFERROR(INDEX(Data_RiskScores!$E$2:$E$14,MATCH($A5,Data_RiskScores!$A$2:$A$14,0)),"") -> 2026-08 | E5: =IFERROR(SUMIFS(Data_ControlResults!$E$2:$E$148,Data_ControlResults!$A$2:$A$148,$A5,Data_ControlResults!$D$2:$D$148,$D5),"") -> 1120 | F5: =IFERROR(INDEX(Data_RiskScores!$F$2:$F$14,MATCH($A5,Data_RiskScores!$A$2:$A$14,0)),"") -> 0.8545 | G5: =IFERROR(INDEX(Data_RiskScores!$G$2:$G$14,MATCH($A5,Data_RiskScores!$A$2:$A$14,0)),"") -> 0.97 | H5: =IFERROR(INDEX(Data_RiskScores!$N$2:$N$14,MATCH($A5,Data_RiskScores!$A$2:$A$14,0)),"") -> Red | I5: =IFERROR(INDEX(Data_RiskScores!$I$2:$I$14,MATCH($A5,Data_RiskScores!$A$2:$A$14,0)),"") -> 55.3 | J5: =IFERROR(INDEX(Data_RiskScores!$L$2:$L$14,MATCH($A5,Data_RiskScores!$A$2:$A$14,0)),"") -> Medium | K5: =IFERROR(INDEX(Data_RiskScores!$M$2:$M$14,MATCH($A5,Data_RiskScores!$A$2:$A$14,0)),"") -> 111
A6: TC-02 | B6: =IFERROR(INDEX(Data_RiskScores!$B$2:$B$14,MATCH($A6,Data_RiskScores!$A$2:$A$14,0)),"") -> Execution Price Reasonableness | C6: =IFERROR(INDEX(Data_RiskScores!$C$2:$C$14,MATCH($A6,Data_RiskScores!$A$2:$A$14,0)),"") -> Trade Allocation & Execution | D6: =IFERROR(INDEX(Data_RiskScores!$E$2:$E$14,MATCH($A6,Data_RiskScores!$A$2:$A$14,0)),"") -> 2026-08 | E6: =IFERROR(SUMIFS(Data_ControlResults!$E$2:$E$148,Data_ControlResults!$A$2:$A$148,$A6,Data_ControlResults!$D$2:$D$148,$D6),"") -> 1117 | F6: =IFERROR(INDEX(Data_RiskScores!$F$2:$F$14,MATCH($A6,Data_RiskScores!$A$2:$A$14,0)),"") -> 0.9812 | G6: =IFERROR(INDEX(Data_RiskScores!$G$2:$G$14,MATCH($A6,Data_RiskScores!$A$2:$A$14,0)),"") -> 0.98 | H6: =IFERROR(INDEX(Data_RiskScores!$N$2:$N$14,MATCH($A6,Data_RiskScores!$A$2:$A$14,0)),"") -> Green | I6: =IFERROR(INDEX(Data_RiskScores!$I$2:$I$14,MATCH($A6,Data_RiskScores!$A$2:$A$14,0)),"") -> 89 | J6: =IFERROR(INDEX(Data_RiskScores!$L$2:$L$14,MATCH($A6,Data_RiskScores!$A$2:$A$14,0)),"") -> Low | K6: =IFERROR(INDEX(Data_RiskScores!$M$2:$M$14,MATCH($A6,Data_RiskScores!$A$2:$A$14,0)),"") -> 25
A7: TC-03 | B7: =IFERROR(INDEX(Data_RiskScores!$B$2:$B$14,MATCH($A7,Data_RiskScores!$A$2:$A$14,0)),"") -> Pro-Rata Allocation Fairness | C7: =IFERROR(INDEX(Data_RiskScores!$C$2:$C$14,MATCH($A7,Data_RiskScores!$A$2:$A$14,0)),"") -> Trade Allocation & Execution | D7: =IFERROR(INDEX(Data_RiskScores!$E$2:$E$14,MATCH($A7,Data_RiskScores!$A$2:$A$14,0)),"") -> 2026-08 | E7: =IFERROR(SUMIFS(Data_ControlResults!$E$2:$E$148,Data_ControlResults!$A$2:$A$148,$A7,Data_ControlResults!$D$2:$D$148,$D7),"") -> 1120 | F7: =IFERROR(INDEX(Data_RiskScores!$F$2:$F$14,MATCH($A7,Data_RiskScores!$A$2:$A$14,0)),"") -> 0.9545 | G7: =IFERROR(INDEX(Data_RiskScores!$G$2:$G$14,MATCH($A7,Data_RiskScores!$A$2:$A$14,0)),"") -> 0.97 | H7: =IFERROR(INDEX(Data_RiskScores!$N$2:$N$14,MATCH($A7,Data_RiskScores!$A$2:$A$14,0)),"") -> Amber | I7: =IFERROR(INDEX(Data_RiskScores!$I$2:$I$14,MATCH($A7,Data_RiskScores!$A$2:$A$14,0)),"") -> 71.2 | J7: =IFERROR(INDEX(Data_RiskScores!$L$2:$L$14,MATCH($A7,Data_RiskScores!$A$2:$A$14,0)),"") -> Low | K7: =IFERROR(INDEX(Data_RiskScores!$M$2:$M$14,MATCH($A7,Data_RiskScores!$A$2:$A$14,0)),"") -> 92
A8: FC-01 | B8: =IFERROR(INDEX(Data_RiskScores!$B$2:$B$14,MATCH($A8,Data_RiskScores!$A$2:$A$14,0)),"") -> Fee Recalculation Match | C8: =IFERROR(INDEX(Data_RiskScores!$C$2:$C$14,MATCH($A8,Data_RiskScores!$A$2:$A$14,0)),"") -> Fee Billing & Calculation | D8: =IFERROR(INDEX(Data_RiskScores!$E$2:$E$14,MATCH($A8,Data_RiskScores!$A$2:$A$14,0)),"") -> 2026-08 | E8: =IFERROR(SUMIFS(Data_ControlResults!$E$2:$E$148,Data_ControlResults!$A$2:$A$148,$A8,Data_ControlResults!$D$2:$D$148,$D8),"") -> 299 | F8: =IFERROR(INDEX(Data_RiskScores!$F$2:$F$14,MATCH($A8,Data_RiskScores!$A$2:$A$14,0)),"") -> 0.9833 | G8: =IFERROR(INDEX(Data_RiskScores!$G$2:$G$14,MATCH($A8,Data_RiskScores!$A$2:$A$14,0)),"") -> 0.97 | H8: =IFERROR(INDEX(Data_RiskScores!$N$2:$N$14,MATCH($A8,Data_RiskScores!$A$2:$A$14,0)),"") -> Green | I8: =IFERROR(INDEX(Data_RiskScores!$I$2:$I$14,MATCH($A8,Data_RiskScores!$A$2:$A$14,0)),"") -> 86.3 | J8: =IFERROR(INDEX(Data_RiskScores!$L$2:$L$14,MATCH($A8,Data_RiskScores!$A$2:$A$14,0)),"") -> Low | K8: =IFERROR(INDEX(Data_RiskScores!$M$2:$M$14,MATCH($A8,Data_RiskScores!$A$2:$A$14,0)),"") -> 12
A9: FC-02 | B9: =IFERROR(INDEX(Data_RiskScores!$B$2:$B$14,MATCH($A9,Data_RiskScores!$A$2:$A$14,0)),"") -> Invoice Timeliness SLA | C9: =IFERROR(INDEX(Data_RiskScores!$C$2:$C$14,MATCH($A9,Data_RiskScores!$A$2:$A$14,0)),"") -> Fee Billing & Calculation | D9: =IFERROR(INDEX(Data_RiskScores!$E$2:$E$14,MATCH($A9,Data_RiskScores!$A$2:$A$14,0)),"") -> 2026-08 | E9: =IFERROR(SUMIFS(Data_ControlResults!$E$2:$E$148,Data_ControlResults!$A$2:$A$148,$A9,Data_ControlResults!$D$2:$D$148,$D9),"") -> 300 | F9: =IFERROR(INDEX(Data_RiskScores!$F$2:$F$14,MATCH($A9,Data_RiskScores!$A$2:$A$14,0)),"") -> 0.96 | G9: =IFERROR(INDEX(Data_RiskScores!$G$2:$G$14,MATCH($A9,Data_RiskScores!$A$2:$A$14,0)),"") -> 0.95 | H9: =IFERROR(INDEX(Data_RiskScores!$N$2:$N$14,MATCH($A9,Data_RiskScores!$A$2:$A$14,0)),"") -> Green | I9: =IFERROR(INDEX(Data_RiskScores!$I$2:$I$14,MATCH($A9,Data_RiskScores!$A$2:$A$14,0)),"") -> 76.3 | J9: =IFERROR(INDEX(Data_RiskScores!$L$2:$L$14,MATCH($A9,Data_RiskScores!$A$2:$A$14,0)),"") -> Low | K9: =IFERROR(INDEX(Data_RiskScores!$M$2:$M$14,MATCH($A9,Data_RiskScores!$A$2:$A$14,0)),"") -> 28
A10: KC-01 | B10: =IFERROR(INDEX(Data_RiskScores!$B$2:$B$14,MATCH($A10,Data_RiskScores!$A$2:$A$14,0)),"") -> Refresh SLA Compliance | C10: =IFERROR(INDEX(Data_RiskScores!$C$2:$C$14,MATCH($A10,Data_RiskScores!$A$2:$A$14,0)),"") -> Client Onboarding / KYC-AML Refresh | D10: =IFERROR(INDEX(Data_RiskScores!$E$2:$E$14,MATCH($A10,Data_RiskScores!$A$2:$A$14,0)),"") -> 2026-09 | E10: =IFERROR(SUMIFS(Data_ControlResults!$E$2:$E$148,Data_ControlResults!$A$2:$A$148,$A10,Data_ControlResults!$D$2:$D$148,$D10),"") -> 118 | F10: =IFERROR(INDEX(Data_RiskScores!$F$2:$F$14,MATCH($A10,Data_RiskScores!$A$2:$A$14,0)),"") -> 0.661 | G10: =IFERROR(INDEX(Data_RiskScores!$G$2:$G$14,MATCH($A10,Data_RiskScores!$A$2:$A$14,0)),"") -> 0.96 | H10: =IFERROR(INDEX(Data_RiskScores!$N$2:$N$14,MATCH($A10,Data_RiskScores!$A$2:$A$14,0)),"") -> Red | I10: =IFERROR(INDEX(Data_RiskScores!$I$2:$I$14,MATCH($A10,Data_RiskScores!$A$2:$A$14,0)),"") -> 42.4 | J10: =IFERROR(INDEX(Data_RiskScores!$L$2:$L$14,MATCH($A10,Data_RiskScores!$A$2:$A$14,0)),"") -> High | K10: =IFERROR(INDEX(Data_RiskScores!$M$2:$M$14,MATCH($A10,Data_RiskScores!$A$2:$A$14,0)),"") -> 61
A11: KC-02 | B11: =IFERROR(INDEX(Data_RiskScores!$B$2:$B$14,MATCH($A11,Data_RiskScores!$A$2:$A$14,0)),"") -> Documentation Completeness | C11: =IFERROR(INDEX(Data_RiskScores!$C$2:$C$14,MATCH($A11,Data_RiskScores!$A$2:$A$14,0)),"") -> Client Onboarding / KYC-AML Refresh | D11: =IFERROR(INDEX(Data_RiskScores!$E$2:$E$14,MATCH($A11,Data_RiskScores!$A$2:$A$14,0)),"") -> 2026-09 | E11: =IFERROR(SUMIFS(Data_ControlResults!$E$2:$E$148,Data_ControlResults!$A$2:$A$148,$A11,Data_ControlResults!$D$2:$D$148,$D11),"") -> 118 | F11: =IFERROR(INDEX(Data_RiskScores!$F$2:$F$14,MATCH($A11,Data_RiskScores!$A$2:$A$14,0)),"") -> 0.9576 | G11: =IFERROR(INDEX(Data_RiskScores!$G$2:$G$14,MATCH($A11,Data_RiskScores!$A$2:$A$14,0)),"") -> 0.98 | H11: =IFERROR(INDEX(Data_RiskScores!$N$2:$N$14,MATCH($A11,Data_RiskScores!$A$2:$A$14,0)),"") -> Amber | I11: =IFERROR(INDEX(Data_RiskScores!$I$2:$I$14,MATCH($A11,Data_RiskScores!$A$2:$A$14,0)),"") -> 68.6 | J11: =IFERROR(INDEX(Data_RiskScores!$L$2:$L$14,MATCH($A11,Data_RiskScores!$A$2:$A$14,0)),"") -> Medium | K11: =IFERROR(INDEX(Data_RiskScores!$M$2:$M$14,MATCH($A11,Data_RiskScores!$A$2:$A$14,0)),"") -> 9
A12: NV-01 | B12: =IFERROR(INDEX(Data_RiskScores!$B$2:$B$14,MATCH($A12,Data_RiskScores!$A$2:$A$14,0)),"") -> Price Variance Tolerance | C12: =IFERROR(INDEX(Data_RiskScores!$C$2:$C$14,MATCH($A12,Data_RiskScores!$A$2:$A$14,0)),"") -> NAV / Valuation Oversight | D12: =IFERROR(INDEX(Data_RiskScores!$E$2:$E$14,MATCH($A12,Data_RiskScores!$A$2:$A$14,0)),"") -> 2026-08 | E12: =IFERROR(SUMIFS(Data_ControlResults!$E$2:$E$148,Data_ControlResults!$A$2:$A$148,$A12,Data_ControlResults!$D$2:$D$148,$D12),"") -> 420 | F12: =IFERROR(INDEX(Data_RiskScores!$F$2:$F$14,MATCH($A12,Data_RiskScores!$A$2:$A$14,0)),"") -> 0.9762 | G12: =IFERROR(INDEX(Data_RiskScores!$G$2:$G$14,MATCH($A12,Data_RiskScores!$A$2:$A$14,0)),"") -> 0.97 | H12: =IFERROR(INDEX(Data_RiskScores!$N$2:$N$14,MATCH($A12,Data_RiskScores!$A$2:$A$14,0)),"") -> Green | I12: =IFERROR(INDEX(Data_RiskScores!$I$2:$I$14,MATCH($A12,Data_RiskScores!$A$2:$A$14,0)),"") -> 89 | J12: =IFERROR(INDEX(Data_RiskScores!$L$2:$L$14,MATCH($A12,Data_RiskScores!$A$2:$A$14,0)),"") -> Low | K12: =IFERROR(INDEX(Data_RiskScores!$M$2:$M$14,MATCH($A12,Data_RiskScores!$A$2:$A$14,0)),"") -> 12
A13: NV-02 | B13: =IFERROR(INDEX(Data_RiskScores!$B$2:$B$14,MATCH($A13,Data_RiskScores!$A$2:$A$14,0)),"") -> Break Resolution SLA | C13: =IFERROR(INDEX(Data_RiskScores!$C$2:$C$14,MATCH($A13,Data_RiskScores!$A$2:$A$14,0)),"") -> NAV / Valuation Oversight | D13: =IFERROR(INDEX(Data_RiskScores!$E$2:$E$14,MATCH($A13,Data_RiskScores!$A$2:$A$14,0)),"") -> 2026-08 | E13: =IFERROR(SUMIFS(Data_ControlResults!$E$2:$E$148,Data_ControlResults!$A$2:$A$148,$A13,Data_ControlResults!$D$2:$D$148,$D13),"") -> 10 | F13: =IFERROR(INDEX(Data_RiskScores!$F$2:$F$14,MATCH($A13,Data_RiskScores!$A$2:$A$14,0)),"") -> 0.6 | G13: =IFERROR(INDEX(Data_RiskScores!$G$2:$G$14,MATCH($A13,Data_RiskScores!$A$2:$A$14,0)),"") -> 0.9 | H13: =IFERROR(INDEX(Data_RiskScores!$N$2:$N$14,MATCH($A13,Data_RiskScores!$A$2:$A$14,0)),"") -> Red | I13: =IFERROR(INDEX(Data_RiskScores!$I$2:$I$14,MATCH($A13,Data_RiskScores!$A$2:$A$14,0)),"") -> 48 | J13: =IFERROR(INDEX(Data_RiskScores!$L$2:$L$14,MATCH($A13,Data_RiskScores!$A$2:$A$14,0)),"") -> High | K13: =IFERROR(INDEX(Data_RiskScores!$M$2:$M$14,MATCH($A13,Data_RiskScores!$A$2:$A$14,0)),"") -> 2
A14: CM-01 | B14: =IFERROR(INDEX(Data_RiskScores!$B$2:$B$14,MATCH($A14,Data_RiskScores!$A$2:$A$14,0)),"") -> Dual Approval Threshold | C14: =IFERROR(INDEX(Data_RiskScores!$C$2:$C$14,MATCH($A14,Data_RiskScores!$A$2:$A$14,0)),"") -> Cash & Collateral Movements | D14: =IFERROR(INDEX(Data_RiskScores!$E$2:$E$14,MATCH($A14,Data_RiskScores!$A$2:$A$14,0)),"") -> 2026-08 | E14: =IFERROR(SUMIFS(Data_ControlResults!$E$2:$E$148,Data_ControlResults!$A$2:$A$148,$A14,Data_ControlResults!$D$2:$D$148,$D14),"") -> 54 | F14: =IFERROR(INDEX(Data_RiskScores!$F$2:$F$14,MATCH($A14,Data_RiskScores!$A$2:$A$14,0)),"") -> 0.8889 | G14: =IFERROR(INDEX(Data_RiskScores!$G$2:$G$14,MATCH($A14,Data_RiskScores!$A$2:$A$14,0)),"") -> 0.99 | H14: =IFERROR(INDEX(Data_RiskScores!$N$2:$N$14,MATCH($A14,Data_RiskScores!$A$2:$A$14,0)),"") -> Red | I14: =IFERROR(INDEX(Data_RiskScores!$I$2:$I$14,MATCH($A14,Data_RiskScores!$A$2:$A$14,0)),"") -> 63.9 | J14: =IFERROR(INDEX(Data_RiskScores!$L$2:$L$14,MATCH($A14,Data_RiskScores!$A$2:$A$14,0)),"") -> Medium | K14: =IFERROR(INDEX(Data_RiskScores!$M$2:$M$14,MATCH($A14,Data_RiskScores!$A$2:$A$14,0)),"") -> 1
A15: CM-02 | B15: =IFERROR(INDEX(Data_RiskScores!$B$2:$B$14,MATCH($A15,Data_RiskScores!$A$2:$A$14,0)),"") -> Custodian Reconciliation Match | C15: =IFERROR(INDEX(Data_RiskScores!$C$2:$C$14,MATCH($A15,Data_RiskScores!$A$2:$A$14,0)),"") -> Cash & Collateral Movements | D15: =IFERROR(INDEX(Data_RiskScores!$E$2:$E$14,MATCH($A15,Data_RiskScores!$A$2:$A$14,0)),"") -> 2026-08 | E15: =IFERROR(SUMIFS(Data_ControlResults!$E$2:$E$148,Data_ControlResults!$A$2:$A$148,$A15,Data_ControlResults!$D$2:$D$148,$D15),"") -> 292 | F15: =IFERROR(INDEX(Data_RiskScores!$F$2:$F$14,MATCH($A15,Data_RiskScores!$A$2:$A$14,0)),"") -> 0.9829 | G15: =IFERROR(INDEX(Data_RiskScores!$G$2:$G$14,MATCH($A15,Data_RiskScores!$A$2:$A$14,0)),"") -> 0.98 | H15: =IFERROR(INDEX(Data_RiskScores!$N$2:$N$14,MATCH($A15,Data_RiskScores!$A$2:$A$14,0)),"") -> Green | I15: =IFERROR(INDEX(Data_RiskScores!$I$2:$I$14,MATCH($A15,Data_RiskScores!$A$2:$A$14,0)),"") -> 87.3 | J15: =IFERROR(INDEX(Data_RiskScores!$L$2:$L$14,MATCH($A15,Data_RiskScores!$A$2:$A$14,0)),"") -> Low | K15: =IFERROR(INDEX(Data_RiskScores!$M$2:$M$14,MATCH($A15,Data_RiskScores!$A$2:$A$14,0)),"") -> 6
A16: SM-01 | B16: =IFERROR(INDEX(Data_RiskScores!$B$2:$B$14,MATCH($A16,Data_RiskScores!$A$2:$A$14,0)),"") -> Guideline Band Compliance | C16: =IFERROR(INDEX(Data_RiskScores!$C$2:$C$14,MATCH($A16,Data_RiskScores!$A$2:$A$14,0)),"") -> Suitability & Mandate Compliance | D16: =IFERROR(INDEX(Data_RiskScores!$E$2:$E$14,MATCH($A16,Data_RiskScores!$A$2:$A$14,0)),"") -> 2026-08 | E16: =IFERROR(SUMIFS(Data_ControlResults!$E$2:$E$148,Data_ControlResults!$A$2:$A$148,$A16,Data_ControlResults!$D$2:$D$148,$D16),"") -> 450 | F16: =IFERROR(INDEX(Data_RiskScores!$F$2:$F$14,MATCH($A16,Data_RiskScores!$A$2:$A$14,0)),"") -> 0.9422 | G16: =IFERROR(INDEX(Data_RiskScores!$G$2:$G$14,MATCH($A16,Data_RiskScores!$A$2:$A$14,0)),"") -> 0.93 | H16: =IFERROR(INDEX(Data_RiskScores!$N$2:$N$14,MATCH($A16,Data_RiskScores!$A$2:$A$14,0)),"") -> Green | I16: =IFERROR(INDEX(Data_RiskScores!$I$2:$I$14,MATCH($A16,Data_RiskScores!$A$2:$A$14,0)),"") -> 84 | J16: =IFERROR(INDEX(Data_RiskScores!$L$2:$L$14,MATCH($A16,Data_RiskScores!$A$2:$A$14,0)),"") -> Low | K16: =IFERROR(INDEX(Data_RiskScores!$M$2:$M$14,MATCH($A16,Data_RiskScores!$A$2:$A$14,0)),"") -> 23
A17: SM-02 | B17: =IFERROR(INDEX(Data_RiskScores!$B$2:$B$14,MATCH($A17,Data_RiskScores!$A$2:$A$14,0)),"") -> Periodic Suitability Review | C17: =IFERROR(INDEX(Data_RiskScores!$C$2:$C$14,MATCH($A17,Data_RiskScores!$A$2:$A$14,0)),"") -> Suitability & Mandate Compliance | D17: =IFERROR(INDEX(Data_RiskScores!$E$2:$E$14,MATCH($A17,Data_RiskScores!$A$2:$A$14,0)),"") -> 2026-08 | E17: =IFERROR(SUMIFS(Data_ControlResults!$E$2:$E$148,Data_ControlResults!$A$2:$A$148,$A17,Data_ControlResults!$D$2:$D$148,$D17),"") -> 10 | F17: =IFERROR(INDEX(Data_RiskScores!$F$2:$F$14,MATCH($A17,Data_RiskScores!$A$2:$A$14,0)),"") -> 1 | G17: =IFERROR(INDEX(Data_RiskScores!$G$2:$G$14,MATCH($A17,Data_RiskScores!$A$2:$A$14,0)),"") -> 0.95 | H17: =IFERROR(INDEX(Data_RiskScores!$N$2:$N$14,MATCH($A17,Data_RiskScores!$A$2:$A$14,0)),"") -> Green | I17: =IFERROR(INDEX(Data_RiskScores!$I$2:$I$14,MATCH($A17,Data_RiskScores!$A$2:$A$14,0)),"") -> 92 | J17: =IFERROR(INDEX(Data_RiskScores!$L$2:$L$14,MATCH($A17,Data_RiskScores!$A$2:$A$14,0)),"") -> Low | K17: =IFERROR(INDEX(Data_RiskScores!$M$2:$M$14,MATCH($A17,Data_RiskScores!$A$2:$A$14,0)),"") -> 0

Sheet KRI Trend
A1: AegisIQ — KRI Pass-Rate Trend
A2: Monthly pass rate by control, live from Data_ControlResults
A4: Control ID | B4: 2025-09 | C4: 2025-10 | D4: 2025-11 | E4: 2025-12 | F4: 2026-01 | G4: 2026-02 | H4: 2026-03 | I4: 2026-04 | J4: 2026-05 | K4: 2026-06 | L4: 2026-07 | M4: 2026-08 | N4: 2026-09
A5: TC-01 | B5: =IFERROR(AVERAGEIFS(Data_ControlResults!$I$2:$I$148,Data_ControlResults!$A$2:$A$148,$A5,Data_ControlResults!$D$2:$D$148,B$4),"") -> 0.9874 | C5: =IFERROR(AVERAGEIFS(Data_ControlResults!$I$2:$I$148,Data_ControlResults!$A$2:$A$148,$A5,Data_ControlResults!$D$2:$D$148,C$4),"") -> 0.9884 | D5: =IFERROR(AVERAGEIFS(Data_ControlResults!$I$2:$I$148,Data_ControlResults!$A$2:$A$148,$A5,Data_ControlResults!$D$2:$D$148,D$4),"") -> 0.9896 | E5: =IFERROR(AVERAGEIFS(Data_ControlResults!$I$2:$I$148,Data_ControlResults!$A$2:$A$148,$A5,Data_ControlResults!$D$2:$D$148,E$4),"") -> 0.9905 | F5: =IFERROR(AVERAGEIFS(Data_ControlResults!$I$2:$I$148,Data_ControlResults!$A$2:$A$148,$A5,Data_ControlResults!$D$2:$D$148,F$4),"") -> 0.9914 | G5: =IFERROR(AVERAGEIFS(Data_ControlResults!$I$2:$I$148,Data_ControlResults!$A$2:$A$148,$A5,Data_ControlResults!$D$2:$D$148,G$4),"") -> 0.99 | H5: =IFERROR(AVERAGEIFS(Data_ControlResults!$I$2:$I$148,Data_ControlResults!$A$2:$A$148,$A5,Data_ControlResults!$D$2:$D$148,H$4),"") -> 0.9896 | I5: =IFERROR(AVERAGEIFS(Data_ControlResults!$I$2:$I$148,Data_ControlResults!$A$2:$A$148,$A5,Data_ControlResults!$D$2:$D$148,I$4),"") -> 0.9896 | ... N5: =IFERROR(AVERAGEIFS(Data_ControlResults!$I$2:$I$148,Data_ControlResults!$A$2:$A$148,$A5,Data_ControlResults!$D$2:$D$148,N$4),"")
A6: TC-02 | B6: =IFERROR(AVERAGEIFS(Data_ControlResults!$I$2:$I$148,Data_ControlResults!$A$2:$A$148,$A6,Data_ControlResults!$D$2:$D$148,B$4),"") -> 0.9815 | C6: =IFERROR(AVERAGEIFS(Data_ControlResults!$I$2:$I$148,Data_ControlResults!$A$2:$A$148,$A6,Data_ControlResults!$D$2:$D$148,C$4),"") -> 0.9751 | D6: =IFERROR(AVERAGEIFS(Data_ControlResults!$I$2:$I$148,Data_ControlResults!$A$2:$A$148,$A6,Data_ControlResults!$D$2:$D$148,D$4),"") -> 0.9867 | E6: =IFERROR(AVERAGEIFS(Data_ControlResults!$I$2:$I$148,Data_ControlResults!$A$2:$A$148,$A6,Data_ControlResults!$D$2:$D$148,E$4),"") -> 0.9849 | F6: =IFERROR(AVERAGEIFS(Data_ControlResults!$I$2:$I$148,Data_ControlResults!$A$2:$A$148,$A6,Data_ControlResults!$D$2:$D$148,F$4),"") -> 0.9905 | G6: =IFERROR(AVERAGEIFS(Data_ControlResults!$I$2:$I$148,Data_ControlResults!$A$2:$A$148,$A6,Data_ControlResults!$D$2:$D$148,G$4),"") -> 0.9909 | H6: =IFERROR(AVERAGEIFS(Data_ControlResults!$I$2:$I$148,Data_ControlResults!$A$2:$A$148,$A6,Data_ControlResults!$D$2:$D$148,H$4),"") -> 0.987 | I6: =IFERROR(AVERAGEIFS(Data_ControlResults!$I$2:$I$148,Data_ControlResults!$A$2:$A$148,$A6,Data_ControlResults!$D$2:$D$148,I$4),"") -> 0.9852 | ... N6: =IFERROR(AVERAGEIFS(Data_ControlResults!$I$2:$I$148,Data_ControlResults!$A$2:$A$148,$A6,Data_ControlResults!$D$2:$D$148,N$4),"")
A7: TC-03 | B7: =IFERROR(AVERAGEIFS(Data_ControlResults!$I$2:$I$148,Data_ControlResults!$A$2:$A$148,$A7,Data_ControlResults!$D$2:$D$148,B$4),"") -> 0.9386 | C7: =IFERROR(AVERAGEIFS(Data_ControlResults!$I$2:$I$148,Data_ControlResults!$A$2:$A$148,$A7,Data_ControlResults!$D$2:$D$148,C$4),"") -> 0.9449 | D7: =IFERROR(AVERAGEIFS(Data_ControlResults!$I$2:$I$148,Data_ControlResults!$A$2:$A$148,$A7,Data_ControlResults!$D$2:$D$148,D$4),"") -> 0.9471 | E7: =IFERROR(AVERAGEIFS(Data_ControlResults!$I$2:$I$148,Data_ControlResults!$A$2:$A$148,$A7,Data_ControlResults!$D$2:$D$148,E$4),"") -> 0.9485 | F7: =IFERROR(AVERAGEIFS(Data_ControlResults!$I$2:$I$148,Data_ControlResults!$A$2:$A$148,$A7,Data_ControlResults!$D$2:$D$148,F$4),"") -> 0.9333 | G7: =IFERROR(AVERAGEIFS(Data_ControlResults!$I$2:$I$148,Data_ControlResults!$A$2:$A$148,$A7,Data_ControlResults!$D$2:$D$148,G$4),"") -> 0.9534 | H7: =IFERROR(AVERAGEIFS(Data_ControlResults!$I$2:$I$148,Data_ControlResults!$A$2:$A$148,$A7,Data_ControlResults!$D$2:$D$148,H$4),"") -> 0.9429 | I7: =IFERROR(AVERAGEIFS(Data_ControlResults!$I$2:$I$148,Data_ControlResults!$A$2:$A$148,$A7,Data_ControlResults!$D$2:$D$148,I$4),"") -> 0.949 | ... N7: =IFERROR(AVERAGEIFS(Data_ControlResults!$I$2:$I$148,Data_ControlResults!$A$2:$A$148,$A7,Data_ControlResults!$D$2:$D$148,N$4),"")
A8: FC-01 | B8: =IFERROR(AVERAGEIFS(Data_ControlResults!$I$2:$I$148,Data_ControlResults!$A$2:$A$148,$A8,Data_ControlResults!$D$2:$D$148,B$4),"") -> 0.9865 | C8: =IFERROR(AVERAGEIFS(Data_ControlResults!$I$2:$I$148,Data_ControlResults!$A$2:$A$148,$A8,Data_ControlResults!$D$2:$D$148,C$4),"") -> 0.9731 | D8: =IFERROR(AVERAGEIFS(Data_ControlResults!$I$2:$I$148,Data_ControlResults!$A$2:$A$148,$A8,Data_ControlResults!$D$2:$D$148,D$4),"") -> 0.9866 | E8: =IFERROR(AVERAGEIFS(Data_ControlResults!$I$2:$I$148,Data_ControlResults!$A$2:$A$148,$A8,Data_ControlResults!$D$2:$D$148,E$4),"") -> 0.9797 | F8: =IFERROR(AVERAGEIFS(Data_ControlResults!$I$2:$I$148,Data_ControlResults!$A$2:$A$148,$A8,Data_ControlResults!$D$2:$D$148,F$4),"") -> 0.9831 | G8: =IFERROR(AVERAGEIFS(Data_ControlResults!$I$2:$I$148,Data_ControlResults!$A$2:$A$148,$A8,Data_ControlResults!$D$2:$D$148,G$4),"") -> 0.7625 | H8: =IFERROR(AVERAGEIFS(Data_ControlResults!$I$2:$I$148,Data_ControlResults!$A$2:$A$148,$A8,Data_ControlResults!$D$2:$D$148,H$4),"") -> 0.9799 | I8: =IFERROR(AVERAGEIFS(Data_ControlResults!$I$2:$I$148,Data_ControlResults!$A$2:$A$148,$A8,Data_ControlResults!$D$2:$D$148,I$4),"") -> 0.9899 | ... N8: =IFERROR(AVERAGEIFS(Data_ControlResults!$I$2:$I$148,Data_ControlResults!$A$2:$A$148,$A8,Data_ControlResults!$D$2:$D$148,N$4),"")
A9: FC-02 | B9: =IFERROR(AVERAGEIFS(Data_ControlResults!$I$2:$I$148,Data_ControlResults!$A$2:$A$148,$A9,Data_ControlResults!$D$2:$D$148,B$4),"") -> 0.9367 | C9: =IFERROR(AVERAGEIFS(Data_ControlResults!$I$2:$I$148,Data_ControlResults!$A$2:$A$148,$A9,Data_ControlResults!$D$2:$D$148,C$4),"") -> 0.9667 | D9: =IFERROR(AVERAGEIFS(Data_ControlResults!$I$2:$I$148,Data_ControlResults!$A$2:$A$148,$A9,Data_ControlResults!$D$2:$D$148,D$4),"") -> 0.97 | E9: =IFERROR(AVERAGEIFS(Data_ControlResults!$I$2:$I$148,Data_ControlResults!$A$2:$A$148,$A9,Data_ControlResults!$D$2:$D$148,E$4),"") -> 0.9767 | F9: =IFERROR(AVERAGEIFS(Data_ControlResults!$I$2:$I$148,Data_ControlResults!$A$2:$A$148,$A9,Data_ControlResults!$D$2:$D$148,F$4),"") -> 0.9733 | G9: =IFERROR(AVERAGEIFS(Data_ControlResults!$I$2:$I$148,Data_ControlResults!$A$2:$A$148,$A9,Data_ControlResults!$D$2:$D$148,G$4),"") -> 0.9633 | H9: =IFERROR(AVERAGEIFS(Data_ControlResults!$I$2:$I$148,Data_ControlResults!$A$2:$A$148,$A9,Data_ControlResults!$D$2:$D$148,H$4),"") -> 0.98 | I9: =IFERROR(AVERAGEIFS(Data_ControlResults!$I$2:$I$148,Data_ControlResults!$A$2:$A$148,$A9,Data_ControlResults!$D$2:$D$148,I$4),"") -> 0.9467 | ... N9: =IFERROR(AVERAGEIFS(Data_ControlResults!$I$2:$I$148,Data_ControlResults!$A$2:$A$148,$A9,Data_ControlResults!$D$2:$D$148,N$4),"")
A10: KC-01 | B10: =IFERROR(AVERAGEIFS(Data_ControlResults!$I$2:$I$148,Data_ControlResults!$A$2:$A$148,$A10,Data_ControlResults!$D$2:$D$148,B$4),"") -> 1 | C10: =IFERROR(AVERAGEIFS(Data_ControlResults!$I$2:$I$148,Data_ControlResults!$A$2:$A$148,$A10,Data_ControlResults!$D$2:$D$148,C$4),"") -> 0.9632 | D10: =IFERROR(AVERAGEIFS(Data_ControlResults!$I$2:$I$148,Data_ControlResults!$A$2:$A$148,$A10,Data_ControlResults!$D$2:$D$148,D$4),"") -> 0.9463 | E10: =IFERROR(AVERAGEIFS(Data_ControlResults!$I$2:$I$148,Data_ControlResults!$A$2:$A$148,$A10,Data_ControlResults!$D$2:$D$148,E$4),"") -> 0.986 | F10: =IFERROR(AVERAGEIFS(Data_ControlResults!$I$2:$I$148,Data_ControlResults!$A$2:$A$148,$A10,Data_ControlResults!$D$2:$D$148,F$4),"") -> 0.9623 | G10: =IFERROR(AVERAGEIFS(Data_ControlResults!$I$2:$I$148,Data_ControlResults!$A$2:$A$148,$A10,Data_ControlResults!$D$2:$D$148,G$4),"") -> 0.95 | H10: =IFERROR(AVERAGEIFS(Data_ControlResults!$I$2:$I$148,Data_ControlResults!$A$2:$A$148,$A10,Data_ControlResults!$D$2:$D$148,H$4),"") -> 0.9536 | I10: =IFERROR(AVERAGEIFS(Data_ControlResults!$I$2:$I$148,Data_ControlResults!$A$2:$A$148,$A10,Data_ControlResults!$D$2:$D$148,I$4),"") -> 0.9467 | ... N10: =IFERROR(AVERAGEIFS(Data_ControlResults!$I$2:$I$148,Data_ControlResults!$A$2:$A$148,$A10,Data_ControlResults!$D$2:$D$148,N$4),"") -> 0.661
A11: KC-02 | B11: =IFERROR(AVERAGEIFS(Data_ControlResults!$I$2:$I$148,Data_ControlResults!$A$2:$A$148,$A11,Data_ControlResults!$D$2:$D$148,B$4),"") -> 1 | C11: =IFERROR(AVERAGEIFS(Data_ControlResults!$I$2:$I$148,Data_ControlResults!$A$2:$A$148,$A11,Data_ControlResults!$D$2:$D$148,C$4),"") -> 0.9387 | D11: =IFERROR(AVERAGEIFS(Data_ControlResults!$I$2:$I$148,Data_ControlResults!$A$2:$A$148,$A11,Data_ControlResults!$D$2:$D$148,D$4),"") -> 0.9664 | E11: =IFERROR(AVERAGEIFS(Data_ControlResults!$I$2:$I$148,Data_ControlResults!$A$2:$A$148,$A11,Data_ControlResults!$D$2:$D$148,E$4),"") -> 0.951 | F11: =IFERROR(AVERAGEIFS(Data_ControlResults!$I$2:$I$148,Data_ControlResults!$A$2:$A$148,$A11,Data_ControlResults!$D$2:$D$148,F$4),"") -> 0.9623 | G11: =IFERROR(AVERAGEIFS(Data_ControlResults!$I$2:$I$148,Data_ControlResults!$A$2:$A$148,$A11,Data_ControlResults!$D$2:$D$148,G$4),"") -> 0.9714 | H11: =IFERROR(AVERAGEIFS(Data_ControlResults!$I$2:$I$148,Data_ControlResults!$A$2:$A$148,$A11,Data_ControlResults!$D$2:$D$148,H$4),"") -> 0.947 | I11: =IFERROR(AVERAGEIFS(Data_ControlResults!$I$2:$I$148,Data_ControlResults!$A$2:$A$148,$A11,Data_ControlResults!$D$2:$D$148,I$4),"") -> 0.98 | ... N11: =IFERROR(AVERAGEIFS(Data_ControlResults!$I$2:$I$148,Data_ControlResults!$A$2:$A$148,$A11,Data_ControlResults!$D$2:$D$148,N$4),"") -> 0.9576
A12: NV-01 | B12: =IFERROR(AVERAGEIFS(Data_ControlResults!$I$2:$I$148,Data_ControlResults!$A$2:$A$148,$A12,Data_ControlResults!$D$2:$D$148,B$4),"") -> 0.9773 | C12: =IFERROR(AVERAGEIFS(Data_ControlResults!$I$2:$I$148,Data_ControlResults!$A$2:$A$148,$A12,Data_ControlResults!$D$2:$D$148,C$4),"") -> 0.9891 | D12: =IFERROR(AVERAGEIFS(Data_ControlResults!$I$2:$I$148,Data_ControlResults!$A$2:$A$148,$A12,Data_ControlResults!$D$2:$D$148,D$4),"") -> 0.985 | E12: =IFERROR(AVERAGEIFS(Data_ControlResults!$I$2:$I$148,Data_ControlResults!$A$2:$A$148,$A12,Data_ControlResults!$D$2:$D$148,E$4),"") -> 0.9826 | F12: =IFERROR(AVERAGEIFS(Data_ControlResults!$I$2:$I$148,Data_ControlResults!$A$2:$A$148,$A12,Data_ControlResults!$D$2:$D$148,F$4),"") -> 0.9795 | G12: =IFERROR(AVERAGEIFS(Data_ControlResults!$I$2:$I$148,Data_ControlResults!$A$2:$A$148,$A12,Data_ControlResults!$D$2:$D$148,G$4),"") -> 0.985 | H12: =IFERROR(AVERAGEIFS(Data_ControlResults!$I$2:$I$148,Data_ControlResults!$A$2:$A$148,$A12,Data_ControlResults!$D$2:$D$148,H$4),"") -> 0.975 | I12: =IFERROR(AVERAGEIFS(Data_ControlResults!$I$2:$I$148,Data_ControlResults!$A$2:$A$148,$A12,Data_ControlResults!$D$2:$D$148,I$4),"") -> 0.9864 | ... N12: =IFERROR(AVERAGEIFS(Data_ControlResults!$I$2:$I$148,Data_ControlResults!$A$2:$A$148,$A12,Data_ControlResults!$D$2:$D$148,N$4),"")
A13: NV-02 | B13: =IFERROR(AVERAGEIFS(Data_ControlResults!$I$2:$I$148,Data_ControlResults!$A$2:$A$148,$A13,Data_ControlResults!$D$2:$D$148,B$4),"") -> 0.8 | C13: =IFERROR(AVERAGEIFS(Data_ControlResults!$I$2:$I$148,Data_ControlResults!$A$2:$A$148,$A13,Data_ControlResults!$D$2:$D$148,C$4),"") -> 1 | D13: =IFERROR(AVERAGEIFS(Data_ControlResults!$I$2:$I$148,Data_ControlResults!$A$2:$A$148,$A13,Data_ControlResults!$D$2:$D$148,D$4),"") -> 0.8333 | E13: =IFERROR(AVERAGEIFS(Data_ControlResults!$I$2:$I$148,Data_ControlResults!$A$2:$A$148,$A13,Data_ControlResults!$D$2:$D$148,E$4),"") -> 1 | F13: =IFERROR(AVERAGEIFS(Data_ControlResults!$I$2:$I$148,Data_ControlResults!$A$2:$A$148,$A13,Data_ControlResults!$D$2:$D$148,F$4),"") -> 1 | G13: =IFERROR(AVERAGEIFS(Data_ControlResults!$I$2:$I$148,Data_ControlResults!$A$2:$A$148,$A13,Data_ControlResults!$D$2:$D$148,G$4),"") -> 0.6667 | H13: =IFERROR(AVERAGEIFS(Data_ControlResults!$I$2:$I$148,Data_ControlResults!$A$2:$A$148,$A13,Data_ControlResults!$D$2:$D$148,H$4),"") -> 1 | I13: =IFERROR(AVERAGEIFS(Data_ControlResults!$I$2:$I$148,Data_ControlResults!$A$2:$A$148,$A13,Data_ControlResults!$D$2:$D$148,I$4),"") -> 1 | ... N13: =IFERROR(AVERAGEIFS(Data_ControlResults!$I$2:$I$148,Data_ControlResults!$A$2:$A$148,$A13,Data_ControlResults!$D$2:$D$148,N$4),"")
A14: CM-01 | B14: =IFERROR(AVERAGEIFS(Data_ControlResults!$I$2:$I$148,Data_ControlResults!$A$2:$A$148,$A14,Data_ControlResults!$D$2:$D$148,B$4),"") -> 0.9459 | C14: =IFERROR(AVERAGEIFS(Data_ControlResults!$I$2:$I$148,Data_ControlResults!$A$2:$A$148,$A14,Data_ControlResults!$D$2:$D$148,C$4),"") -> 0.9459 | D14: =IFERROR(AVERAGEIFS(Data_ControlResults!$I$2:$I$148,Data_ControlResults!$A$2:$A$148,$A14,Data_ControlResults!$D$2:$D$148,D$4),"") -> 0.9701 | E14: =IFERROR(AVERAGEIFS(Data_ControlResults!$I$2:$I$148,Data_ControlResults!$A$2:$A$148,$A14,Data_ControlResults!$D$2:$D$148,E$4),"") -> 0.961 | F14: =IFERROR(AVERAGEIFS(Data_ControlResults!$I$2:$I$148,Data_ControlResults!$A$2:$A$148,$A14,Data_ControlResults!$D$2:$D$148,F$4),"") -> 0.9429 | G14: =IFERROR(AVERAGEIFS(Data_ControlResults!$I$2:$I$148,Data_ControlResults!$A$2:$A$148,$A14,Data_ControlResults!$D$2:$D$148,G$4),"") -> 0.9531 | H14: =IFERROR(AVERAGEIFS(Data_ControlResults!$I$2:$I$148,Data_ControlResults!$A$2:$A$148,$A14,Data_ControlResults!$D$2:$D$148,H$4),"") -> 0.9697 | I14: =IFERROR(AVERAGEIFS(Data_ControlResults!$I$2:$I$148,Data_ControlResults!$A$2:$A$148,$A14,Data_ControlResults!$D$2:$D$148,I$4),"") -> 0.9268 | ... N14: =IFERROR(AVERAGEIFS(Data_ControlResults!$I$2:$I$148,Data_ControlResults!$A$2:$A$148,$A14,Data_ControlResults!$D$2:$D$148,N$4),"")
A15: CM-02 | B15: =IFERROR(AVERAGEIFS(Data_ControlResults!$I$2:$I$148,Data_ControlResults!$A$2:$A$148,$A15,Data_ControlResults!$D$2:$D$148,B$4),"") -> 0.9822 | C15: =IFERROR(AVERAGEIFS(Data_ControlResults!$I$2:$I$148,Data_ControlResults!$A$2:$A$148,$A15,Data_ControlResults!$D$2:$D$148,C$4),"") -> 0.9777 | D15: =IFERROR(AVERAGEIFS(Data_ControlResults!$I$2:$I$148,Data_ControlResults!$A$2:$A$148,$A15,Data_ControlResults!$D$2:$D$148,D$4),"") -> 0.9706 | E15: =IFERROR(AVERAGEIFS(Data_ControlResults!$I$2:$I$148,Data_ControlResults!$A$2:$A$148,$A15,Data_ControlResults!$D$2:$D$148,E$4),"") -> 0.9884 | F15: =IFERROR(AVERAGEIFS(Data_ControlResults!$I$2:$I$148,Data_ControlResults!$A$2:$A$148,$A15,Data_ControlResults!$D$2:$D$148,F$4),"") -> 0.9873 | G15: =IFERROR(AVERAGEIFS(Data_ControlResults!$I$2:$I$148,Data_ControlResults!$A$2:$A$148,$A15,Data_ControlResults!$D$2:$D$148,G$4),"") -> 0.9862 | H15: =IFERROR(AVERAGEIFS(Data_ControlResults!$I$2:$I$148,Data_ControlResults!$A$2:$A$148,$A15,Data_ControlResults!$D$2:$D$148,H$4),"") -> 0.9859 | I15: =IFERROR(AVERAGEIFS(Data_ControlResults!$I$2:$I$148,Data_ControlResults!$A$2:$A$148,$A15,Data_ControlResults!$D$2:$D$148,I$4),"") -> 0.9815 | ... N15: =IFERROR(AVERAGEIFS(Data_ControlResults!$I$2:$I$148,Data_ControlResults!$A$2:$A$148,$A15,Data_ControlResults!$D$2:$D$148,N$4),"")
A16: SM-01 | B16: =IFERROR(AVERAGEIFS(Data_ControlResults!$I$2:$I$148,Data_ControlResults!$A$2:$A$148,$A16,Data_ControlResults!$D$2:$D$148,B$4),"") | C16: =IFERROR(AVERAGEIFS(Data_ControlResults!$I$2:$I$148,Data_ControlResults!$A$2:$A$148,$A16,Data_ControlResults!$D$2:$D$148,C$4),"") | D16: =IFERROR(AVERAGEIFS(Data_ControlResults!$I$2:$I$148,Data_ControlResults!$A$2:$A$148,$A16,Data_ControlResults!$D$2:$D$148,D$4),"") | E16: =IFERROR(AVERAGEIFS(Data_ControlResults!$I$2:$I$148,Data_ControlResults!$A$2:$A$148,$A16,Data_ControlResults!$D$2:$D$148,E$4),"") | F16: =IFERROR(AVERAGEIFS(Data_ControlResults!$I$2:$I$148,Data_ControlResults!$A$2:$A$148,$A16,Data_ControlResults!$D$2:$D$148,F$4),"") | G16: =IFERROR(AVERAGEIFS(Data_ControlResults!$I$2:$I$148,Data_ControlResults!$A$2:$A$148,$A16,Data_ControlResults!$D$2:$D$148,G$4),"") | H16: =IFERROR(AVERAGEIFS(Data_ControlResults!$I$2:$I$148,Data_ControlResults!$A$2:$A$148,$A16,Data_ControlResults!$D$2:$D$148,H$4),"") | I16: =IFERROR(AVERAGEIFS(Data_ControlResults!$I$2:$I$148,Data_ControlResults!$A$2:$A$148,$A16,Data_ControlResults!$D$2:$D$148,I$4),"") | ... N16: =IFERROR(AVERAGEIFS(Data_ControlResults!$I$2:$I$148,Data_ControlResults!$A$2:$A$148,$A16,Data_ControlResults!$D$2:$D$148,N$4),"")
A17: SM-02 | B17: =IFERROR(AVERAGEIFS(Data_ControlResults!$I$2:$I$148,Data_ControlResults!$A$2:$A$148,$A17,Data_ControlResults!$D$2:$D$148,B$4),"") -> 1 | C17: =IFERROR(AVERAGEIFS(Data_ControlResults!$I$2:$I$148,Data_ControlResults!$A$2:$A$148,$A17,Data_ControlResults!$D$2:$D$148,C$4),"") -> 0.8889 | D17: =IFERROR(AVERAGEIFS(Data_ControlResults!$I$2:$I$148,Data_ControlResults!$A$2:$A$148,$A17,Data_ControlResults!$D$2:$D$148,D$4),"") -> 1 | E17: =IFERROR(AVERAGEIFS(Data_ControlResults!$I$2:$I$148,Data_ControlResults!$A$2:$A$148,$A17,Data_ControlResults!$D$2:$D$148,E$4),"") -> 0.9524 | F17: =IFERROR(AVERAGEIFS(Data_ControlResults!$I$2:$I$148,Data_ControlResults!$A$2:$A$148,$A17,Data_ControlResults!$D$2:$D$148,F$4),"") -> 0.9231 | G17: =IFERROR(AVERAGEIFS(Data_ControlResults!$I$2:$I$148,Data_ControlResults!$A$2:$A$148,$A17,Data_ControlResults!$D$2:$D$148,G$4),"") -> 0.8182 | H17: =IFERROR(AVERAGEIFS(Data_ControlResults!$I$2:$I$148,Data_ControlResults!$A$2:$A$148,$A17,Data_ControlResults!$D$2:$D$148,H$4),"") -> 0.8333 | I17: =IFERROR(AVERAGEIFS(Data_ControlResults!$I$2:$I$148,Data_ControlResults!$A$2:$A$148,$A17,Data_ControlResults!$D$2:$D$148,I$4),"") -> 0.9286 | ... N17: =IFERROR(AVERAGEIFS(Data_ControlResults!$I$2:$I$148,Data_ControlResults!$A$2:$A$148,$A17,Data_ControlResults!$D$2:$D$148,N$4),"")

Sheet Data_ControlResults
A1: control_id | B1: control_name | C1: process_name | D1: period | E1: population | F1: pass_count | G1: fail_count | H1: dq_exception_count | I1: pass_rate | J1: kri_threshold | K1: rag_status
A2: CM-01 | B2: Dual Approval Threshold | C2: Cash & Collateral Movements | D2: 2025-09 | E2: 74 | F2: 70 | G2: 4 | H2: 0 | I2: 0.9459 | J2: 0.99 | K2: Red
A3: CM-01 | B3: Dual Approval Threshold | C3: Cash & Collateral Movements | D3: 2025-10 | E3: 74 | F3: 70 | G3: 4 | H3: 0 | I3: 0.9459 | J3: 0.99 | K3: Red
A4: CM-01 | B4: Dual Approval Threshold | C4: Cash & Collateral Movements | D4: 2025-11 | E4: 67 | F4: 65 | G4: 2 | H4: 0 | I4: 0.9701 | J4: 0.99 | K4: Amber
A5: CM-01 | B5: Dual Approval Threshold | C5: Cash & Collateral Movements | D5: 2025-12 | E5: 77 | F5: 74 | G5: 3 | H5: 0 | I5: 0.961 | J5: 0.99 | K5: Amber
A6: CM-01 | B6: Dual Approval Threshold | C6: Cash & Collateral Movements | D6: 2026-01 | E6: 70 | F6: 66 | G6: 4 | H6: 0 | I6: 0.9429 | J6: 0.99 | K6: Red
A7: CM-01 | B7: Dual Approval Threshold | C7: Cash & Collateral Movements | D7: 2026-02 | E7: 64 | F7: 61 | G7: 3 | H7: 0 | I7: 0.9531 | J7: 0.99 | K7: Red
A8: CM-01 | B8: Dual Approval Threshold | C8: Cash & Collateral Movements | D8: 2026-03 | E8: 66 | F8: 64 | G8: 2 | H8: 0 | I8: 0.9697 | J8: 0.99 | K8: Amber
A9: CM-01 | B9: Dual Approval Threshold | C9: Cash & Collateral Movements | D9: 2026-04 | E9: 82 | F9: 76 | G9: 6 | H9: 0 | I9: 0.9268 | J9: 0.99 | K9: Red
A10: CM-01 | B10: Dual Approval Threshold | C10: Cash & Collateral Movements | D10: 2026-05 | E10: 75 | F10: 71 | G10: 4 | H10: 0 | I10: 0.9467 | J10: 0.99 | K10: Red
A11: CM-01 | B11: Dual Approval Threshold | C11: Cash & Collateral Movements | D11: 2026-06 | E11: 81 | F11: 77 | G11: 4 | H11: 0 | I11: 0.9506 | J11: 0.99 | K11: Red
A12: CM-01 | B12: Dual Approval Threshold | C12: Cash & Collateral Movements | D12: 2026-07 | E12: 82 | F12: 79 | G12: 3 | H12: 0 | I12: 0.9634 | J12: 0.99 | K12: Amber
A13: CM-01 | B13: Dual Approval Threshold | C13: Cash & Collateral Movements | D13: 2026-08 | E13: 54 | F13: 48 | G13: 6 | H13: 0 | I13: 0.8889 | J13: 0.99 | K13: Red
... A148: TC-03 | B148: Pro-Rata Allocation Fairness | C148: Trade Allocation & Execution | D148: 2026-08 | E148: 1120 | F148: 1069 | G148: 51 | H148: 0 | I148: 0.9545 | J148: 0.97 | K148: Amber

Sheet Data_RiskScores
A1: control_id | B1: control_name | C1: process_name | D1: risk_category | E1: period | F1: latest_pass_rate | G1: kri_threshold | H1: inherent_risk_1to5 | I1: control_effectiveness_score | J1: control_effectiveness_rating | K1: residual_risk_score | L1: residual_risk_rating | M1: open_exceptions | N1: rag_status_latest
A2: KC-01 | B2: Refresh SLA Compliance | C2: Client Onboarding / KYC-AML Refresh | D2: Compliance | E2: 2026-09 | F2: 0.661 | G2: 0.96 | H2: 4 | I2: 42.4 | J2: Ineffective | K2: 11.52 | L2: High | M2: 61 | N2: Red
A3: NV-02 | B3: Break Resolution SLA | C3: NAV / Valuation Oversight | D3: Valuation | E3: 2026-08 | F3: 0.6 | G3: 0.9 | H3: 4 | I3: 48 | J3: Ineffective | K3: 10.4 | L3: High | M3: 2 | N3: Red
A4: TC-01 | B4: Allocation Timeliness | C4: Trade Allocation & Execution | D4: Operational | E4: 2026-08 | F4: 0.8545 | G4: 0.97 | H4: 3 | I4: 55.3 | J4: Ineffective | K4: 6.71 | L4: Medium | M4: 111 | N4: Red
A5: KC-02 | B5: Documentation Completeness | C5: Client Onboarding / KYC-AML Refresh | D5: Compliance | E5: 2026-09 | F5: 0.9576 | G5: 0.98 | H5: 4 | I5: 68.6 | J5: Needs Improvement | K5: 6.28 | L5: Medium | M5: 9 | N5: Amber
A6: CM-01 | B6: Dual Approval Threshold | C6: Cash & Collateral Movements | D6: Operational | E6: 2026-08 | F6: 0.8889 | G6: 0.99 | H6: 3 | I6: 63.9 | J6: Ineffective | K6: 5.42 | L6: Medium | M6: 1 | N6: Red
A7: TC-03 | B7: Pro-Rata Allocation Fairness | C7: Trade Allocation & Execution | D7: Operational | E7: 2026-08 | F7: 0.9545 | G7: 0.97 | H7: 3 | I7: 71.2 | J7: Needs Improvement | K7: 4.32 | L7: Low | M7: 92 | N7: Amber
A8: FC-02 | B8: Invoice Timeliness SLA | C8: Fee Billing & Calculation | D8: Operational | E8: 2026-08 | F8: 0.96 | G8: 0.95 | H8: 3 | I8: 76.3 | J8: Needs Improvement | K8: 3.55 | L8: Low | M8: 28 | N8: Green
A9: SM-01 | B9: Guideline Band Compliance | C9: Suitability & Mandate Compliance | D9: Suitability | E9: 2026-08 | F9: 0.9422 | G9: 0.93 | H9: 4 | I9: 84 | J9: Needs Improvement | K9: 3.2 | L9: Low | M9: 23 | N9: Green
A10: NV-01 | B10: Price Variance Tolerance | C10: NAV / Valuation Oversight | D10: Valuation | E10: 2026-08 | F10: 0.9762 | G10: 0.97 | H10: 4 | I10: 89 | J10: Effective | K10: 2.2 | L10: Low | M10: 12 | N10: Green
A11: FC-01 | B11: Fee Recalculation Match | C11: Fee Billing & Calculation | D11: Operational | E11: 2026-08 | F11: 0.9833 | G11: 0.97 | H11: 3 | I11: 86.3 | J11: Effective | K11: 2.06 | L11: Low | M11: 12 | N11: Green
A12: CM-02 | B12: Custodian Reconciliation Match | C12: Cash & Collateral Movements | D12: Operational | E12: 2026-08 | F12: 0.9829 | G12: 0.98 | H12: 3 | I12: 87.3 | J12: Effective | K12: 1.91 | L12: Low | M12: 6 | N12: Green
A13: TC-02 | B13: Execution Price Reasonableness | C13: Trade Allocation & Execution | D13: Operational | E13: 2026-08 | F13: 0.9812 | G13: 0.98 | H13: 3 | I13: 89 | J13: Effective | K13: 1.65 | L13: Low | M13: 25 | N13: Green
A14: SM-02 | B14: Periodic Suitability Review | C14: Suitability & Mandate Compliance | D14: Suitability | E14: 2026-08 | F14: 1 | G14: 0.95 | H14: 3 | I14: 92 | J14: Effective | K14: 1.2 | L14: Low | M14: 0 | N14: Green

Sheet Data_RemediationActions
A1: action_id | B1: exception_id | C1: control_id | D1: owner | E1: reason_code | F1: detail | G1: identified_date | H1: target_closure_date | I1: days_to_target | J1: status_vs_sla | K1: remediation_priority
A2: REM-9000000 | B2: 9000007 | C2: TC-01 | D2: J. Farrow, Trading Ops | E2: ALLOC_LATE | F2: Allocated 111 min after execution (limit 30 min) | G2: 2025-09-11 | H2: 2025-10-01 | I2: -339 | J2: Overdue | K2: Medium
A3: REM-9000001 | B3: 9000024 | C3: TC-01 | D3: J. Farrow, Trading Ops | E3: ALLOC_LATE | F3: Allocated 63 min after execution (limit 30 min) | G3: 2025-10-15 | H3: 2025-11-04 | I3: -305 | J3: Overdue | K3: Medium
A4: REM-9000002 | B4: 9000025 | C4: TC-01 | D4: J. Farrow, Trading Ops | E4: ALLOC_LATE | F4: Allocated 64 min after execution (limit 30 min) | G4: 2025-10-17 | H4: 2025-11-06 | I4: -303 | J4: Overdue | K4: Medium
A5: REM-9000003 | B5: 9000030 | C5: TC-01 | D5: J. Farrow, Trading Ops | E5: ALLOC_LATE | F5: Allocated 46 min after execution (limit 30 min) | G5: 2025-10-31 | H5: 2025-11-20 | I5: -289 | J5: Overdue | K5: Medium
A6: REM-9000004 | B6: 9000033 | C6: TC-01 | D6: J. Farrow, Trading Ops | E6: ALLOC_LATE | F6: Allocated 173 min after execution (limit 30 min) | G6: 2025-11-13 | H6: 2025-12-03 | I6: -276 | J6: Overdue | K6: Medium
A7: REM-9000005 | B7: 9000038 | C7: TC-01 | D7: J. Farrow, Trading Ops | E7: ALLOC_LATE | F7: Allocated 161 min after execution (limit 30 min) | G7: 2025-11-24 | H7: 2025-12-14 | I7: -265 | J7: Overdue | K7: Medium
A8: REM-9000006 | B8: 9000053 | C8: TC-01 | D8: J. Farrow, Trading Ops | E8: ALLOC_LATE | F8: Allocated 171 min after execution (limit 30 min) | G8: 2025-12-29 | H8: 2026-01-18 | I8: -230 | J8: Overdue | K8: Medium
A9: REM-9000007 | B9: 9000061 | C9: TC-01 | D9: J. Farrow, Trading Ops | E9: ALLOC_LATE | F9: Allocated 76 min after execution (limit 30 min) | G9: 2026-01-22 | H9: 2026-02-11 | I9: -206 | J9: Overdue | K9: Medium
A10: REM-9000008 | B10: 9000091 | C10: TC-01 | D10: J. Farrow, Trading Ops | E10: ALLOC_LATE | F10: Allocated 80 min after execution (limit 30 min) | G10: 2026-04-15 | H10: 2026-05-05 | I10: -123 | J10: Overdue | K10: Medium
A11: REM-9000009 | B11: 9000097 | C11: TC-01 | D11: J. Farrow, Trading Ops | E11: ALLOC_LATE | F11: Allocated 192 min after execution (limit 30 min) | G11: 2026-04-29 | H11: 2026-05-19 | I11: -109 | J11: Overdue | K11: Medium
A12: REM-9000010 | B12: 9000098 | C12: TC-01 | D12: J. Farrow, Trading Ops | E12: ALLOC_LATE | F12: Allocated 117 min after execution (limit 30 min) | G12: 2026-04-29 | H12: 2026-05-19 | I12: -109 | J12: Overdue | K12: Medium
A13: REM-9000011 | B13: 9000099 | C13: TC-01 | D13: J. Farrow, Trading Ops | E13: ALLOC_LATE | F13: Allocated 67 min after execution (limit 30 min) | G13: 2026-05-01 | H13: 2026-05-21 | I13: -107 | J13: Overdue | K13: Medium
... A383: REM-9000381 | B383: 9002262 | C383: SM-01 | D383: A. Petrova, Suitability Oversight | E383: GUIDELINE_BREACH | F383: Bond weight 107.36% is above max for Fixed Income Core | G383: 2026-08-31 | H383: 2026-09-20 | I383: 15 | J383: On Track | K383: Medium
